{"status":"done","publicPath":"http://127.0.0.1:8080/","chunks":{"about":[{"name":"js/about.js","publicPath":"http://127.0.0.1:8080/js/about.js","path":"/home/Monde/projects/budget-tracker/frontend/dist/js/about.js"}],"app":[{"name":"bundle.js","publicPath":"http://127.0.0.1:8080/bundle.js","path":"/home/Monde/projects/budget-tracker/frontend/dist/bundle.js"}]},"error":"ModuleError","message":"Module Error (from ./node_modules/eslint-loader/index.js):\nwarning: Replace `·:to=\"{·name:·'expenses.edit',·params:·{·id:·item.id·}·}\">{{·item.name·}}</router-link` with `⏎··················:to=\"{·name:·'expenses.edit',·params:·{·id:·item.id·}·}\"⏎··················>{{·item.name·}}</router-link⏎················` (prettier/prettier) at src/components/Expenses/ExpensesTable.vue:22:29:\n  20 |             <tr v-for=\"item in expenses\" :key=\"item.id\">\n  21 |               <td>\n> 22 |                 <router-link :to=\"{ name: 'expenses.edit', params: { id: item.id } }\">{{ item.name }}</router-link>\n     |                             ^\n  23 |               </td>\n  24 |               <td>{{ item.type_of_expenses }}</td>\n  25 |               <td>{{ item.date }}</td>\n\n\nwarning: Replace `'@/store/actions.type'` with `\"@/store/actions.type\"` (prettier/prettier) at src/components/Expenses/ExpensesTable.vue:44:32:\n  42 | import { mapGetters } from \"vuex\";\n  43 | \n> 44 | import { FETCH_EXPENSES } from '@/store/actions.type';\n     |                                ^\n  45 | \n  46 | export default {\n  47 |   name: \"expenses-table\",\n\n\nwarning: Replace `'expenses',·'current_expense',·'loading'` with `\"expenses\",·\"current_expense\",·\"loading\"` (prettier/prettier) at src/components/Expenses/ExpensesTable.vue:50:20:\n  48 |   methods: {},\n  49 |   computed: {\n> 50 |     ...mapGetters(['expenses', 'current_expense', 'loading'])\n     |                    ^\n  51 |   },\n  52 |   mounted() {\n  53 |     this.$store.dispatch(FETCH_EXPENSES, FETCH_AN_EXPENSE, this.$route.params.id, );\n\n\nwarning: Replace `FETCH_EXPENSES,·FETCH_AN_EXPENSE,·this.$route.params.id,` with `⏎······FETCH_EXPENSES,⏎······FETCH_AN_EXPENSE,⏎······this.$route.params.id⏎···` (prettier/prettier) at src/components/Expenses/ExpensesTable.vue:53:26:\n  51 |   },\n  52 |   mounted() {\n> 53 |     this.$store.dispatch(FETCH_EXPENSES, FETCH_AN_EXPENSE, this.$route.params.id, );\n     |                          ^\n  54 |   }\n  55 | };\n  56 | </script>\n\n\nerror: 'FETCH_AN_EXPENSE' is not defined (no-undef) at src/components/Expenses/ExpensesTable.vue:53:42:\n  51 |   },\n  52 |   mounted() {\n> 53 |     this.$store.dispatch(FETCH_EXPENSES, FETCH_AN_EXPENSE, this.$route.params.id, );\n     |                                          ^\n  54 |   }\n  55 | };\n  56 | </script>\n\n\n1 error and 4 warnings found.\n4 warnings potentially fixable with the `--fix` option."}